psd_batch_process/__init__.py
psd_batch_process/cli.py
psd_batch_process/processor.py
psd_batch_process-0.1.0.dist-info/licenses/LICENSE
tests/__init__.py
tests/test_processor.py
psd_batch_process-0.1.0.dist-info/METADATA
psd_batch_process-0.1.0.dist-info/WHEEL
psd_batch_process-0.1.0.dist-info/entry_points.txt
psd_batch_process-0.1.0.dist-info/top_level.txt
psd_batch_process-0.1.0.dist-info/RECORD
