Metadata-Version: 2.4
Name: psd_batch_process
Version: 0.1.0
Summary: A tool for batch updating text layers in PSD files using CSV data
Home-page: https://github.com/yourusername/psd_batch_process
Author: Ocarina
Author-email: Ocarina1024@gmail.com
Classifier: Programming Language :: Python :: 3
Classifier: License :: OSI Approved :: MIT License
Classifier: Operating System :: Microsoft :: Windows
Requires-Python: >=3.7
License-File: LICENSE
Requires-Dist: pywin32>=306
Requires-Dist: pandas>=2.1.1
Dynamic: author
Dynamic: author-email
Dynamic: classifier
Dynamic: description
Dynamic: description-content-type
Dynamic: home-page
Dynamic: license-file
Dynamic: requires-dist
Dynamic: requires-python
Dynamic: summary
